log_generator/__init__.py
log_generator/generate.py
log_generator/schema.yaml
log_generator-1.0.2.dist-info/LICENSE
log_generator-1.0.2.dist-info/METADATA
log_generator-1.0.2.dist-info/WHEEL
log_generator-1.0.2.dist-info/entry_points.txt
log_generator-1.0.2.dist-info/top_level.txt
log_generator-1.0.2.dist-info/RECORD
