Metadata-Version: 2.1
Name: log-generator
Version: 1.0.2
Summary: Generates dummy logs based on configuration files
Home-page: UNKNOWN
Author: Peter Scopes
Author-email: peter.scopes@nccgroup.com
License: MIT
Platform: any
Classifier: License :: OSI Approved :: MIT License
Classifier: Programming Language :: Python :: 3
Classifier: Programming Language :: Python :: 3.6
Classifier: Programming Language :: Python :: 3.7
Classifier: Operating System :: OS Independent
Requires-Dist: PyYAML (>=5.1.1)
Requires-Dist: jsonschema (>=3.0.0)
